kaist_dataloader/__init__.py
kaist_dataloader/basic.py
kaist_dataloader/pointcloud.py
kaist_dataloader/py.typed
kaist_dataloader-0.1.1.dist-info/WHEEL
kaist_dataloader-0.1.1.dist-info/METADATA
kaist_dataloader-0.1.1.dist-info/RECORD
