Metadata-Version: 2.3
Name: kaist-dataloader
Version: 0.1.1
Summary: Efficient and user-friendly point cloud data loader for the KAIST dataset, supporting multiple coordinate systems and numpy compatibility.
Keywords: kaist,pointcloud,lidar,slam,autonomous driving,dataset
Author: HopeCollector
Author-email: HopeCollector <cmw0249@gmail.com>
License: MIT License
Classifier: Programming Language :: Python :: 3
Classifier: License :: OSI Approved :: MIT License
Classifier: Operating System :: POSIX :: Linux
Classifier: Intended Audience :: Science/Research
Classifier: Topic :: Scientific/Engineering :: Information Analysis
Classifier: Topic :: Software Development :: Libraries :: Python Modules
Requires-Dist: numpy>=2.3.2
Requires-Dist: scipy>=1.16.1
Requires-Python: >=3.12
Project-URL: Documentation, https://github.com/HopeCollector/kaist-dataloader#readme
Project-URL: Homepage, https://github.com/HopeCollector/kaist-dataloader
Project-URL: Source, https://github.com/HopeCollector/kaist-dataloader
